toolbag/__init__.py
toolbag-0.1.1.dist-info/LICENSE
toolbag-0.1.1.dist-info/METADATA
toolbag-0.1.1.dist-info/WHEEL
toolbag-0.1.1.dist-info/top_level.txt
toolbag-0.1.1.dist-info/RECORD
