Metadata-Version: 2.1
Name: toolbag
Version: 0.1.1
Summary: Python toolbag, like a toolbox, but more flexible!
Home-page: https://github.com/shimst3r/toolbag
Author: Nils Müller
Author-email: shimst3r@gmail.com
License: MIT
Platform: UNKNOWN
Classifier: Development Status :: 2 - Pre-Alpha
Classifier: License :: OSI Approved :: MIT License
Classifier: Programming Language :: Python
Classifier: Programming Language :: Python :: 3.7
Classifier: Programming Language :: Python :: 3.8
Requires-Python: >=3.7, <4
Requires-Dist: typer
